linmapper/__init__.py
linmapper-0.0.9.dist-info/Licence.txt
linmapper-0.0.9.dist-info/METADATA
linmapper-0.0.9.dist-info/WHEEL
linmapper-0.0.9.dist-info/top_level.txt
linmapper-0.0.9.dist-info/RECORD
