Metadata-Version: 2.1
Name: linmapper
Version: 0.0.9
Summary: linmapper is a Python package that allows users to transform vertices of complex numbers from one plane (Z) to another plane (f(Z)).
Home-page: 
Author: Supratim Das
Author-email: supratim0707@gmail.com
License: MIT
Keywords: calculator,linear,complex,number,mapping,supratim,das
Classifier: Development Status :: 5 - Production/Stable
Classifier: Intended Audience :: Education
Classifier: Operating System :: Microsoft :: Windows :: Windows 10
Classifier: License :: OSI Approved :: MIT License
Classifier: Programming Language :: Python :: 3
License-File: Licence.txt
Requires-Dist: numpy
